gemseo_jax/__init__.py
gemseo_jax/auto_jax_discipline.py
gemseo_jax/jax_chain.py
gemseo_jax/jax_discipline.py
gemseo_jax/utils.py
gemseo_jax/problems/__init__.py
gemseo_jax/problems/sellar/__init__.py
gemseo_jax/problems/sellar/base.py
gemseo_jax/problems/sellar/sellar_1.py
gemseo_jax/problems/sellar/sellar_2.py
gemseo_jax/problems/sellar/sellar_chain.py
gemseo_jax/problems/sellar/sellar_system.py
gemseo_jax/problems/sobieski/__init__.py
gemseo_jax/problems/sobieski/aerodynamics.py
gemseo_jax/problems/sobieski/base.py
gemseo_jax/problems/sobieski/chain.py
gemseo_jax/problems/sobieski/mission.py
gemseo_jax/problems/sobieski/propulsion.py
gemseo_jax/problems/sobieski/structure.py
gemseo_jax-2.1.1.dist-info/licenses/LICENSE.txt
gemseo_jax-2.1.1.dist-info/METADATA
gemseo_jax-2.1.1.dist-info/WHEEL
gemseo_jax-2.1.1.dist-info/entry_points.txt
gemseo_jax-2.1.1.dist-info/top_level.txt
gemseo_jax-2.1.1.dist-info/RECORD
